{
  "id": 17,
  "title": "Missing Girl",
  "category": "Thriller",
  "emoji": "🔪",
  "plays": "1326K",
  "new": true,
  "duration": "2:02",
  "generated": true,
  "audioPath": "/audio/story-17.mp3",
  "storyText": "Narrator: 10 साल की लड़की गायब हो गई थी। [TENSE]\n\nInspector: CCTV footage check करो। [URGENT]\n\nConstable: Sir, किसी ने उसे park से जाते देखा था। [CALM]\n\nNarrator: Inspector Singh को एक clue मिला। [TENSE]\n\nInspector: यह footprint किसका है? [DETERMINED]\n\nWitness: मैंने एक van देखी थी। [FEARFUL]\n\nNarrator: समय कम था। [URGENT]\n\nInspector: मुझे पता है वह कहाँ है! [EXCITED]\n\nNarrator: और बच्ची को सही-सलामत बचा लिया गया। [INSPIRING]",
  "generatedAt": "2026-02-09T07:48:12.380Z"
}